unittestx/__init__.py
unittestx/app.py
unittestx-0.1.3.dist-info/LICENSE
unittestx-0.1.3.dist-info/METADATA
unittestx-0.1.3.dist-info/WHEEL
unittestx-0.1.3.dist-info/entry_points.txt
unittestx-0.1.3.dist-info/RECORD
