Metadata-Version: 2.1
Name: unittestx
Version: 0.1.3
Summary: A custom unittest runner for Python
Home-page: https://github.com/fullstack-spiderman/unittestx
License: MIT
Keywords: testing,unittest,testrunner
Author: Arjun KayalMoni
Author-email: arjun.umathanu@gmail.com
Maintainer: Arjun KayalMoni
Maintainer-email: arjun.umathanu@gmail.com
Requires-Python: >=3.8,<4.0
Classifier: License :: OSI Approved :: MIT License
Classifier: Programming Language :: Python :: 3
Classifier: Programming Language :: Python :: 3.8
Classifier: Programming Language :: Python :: 3.9
Classifier: Programming Language :: Python :: 3.10
Classifier: Programming Language :: Python :: 3.11
Classifier: Topic :: Software Development :: Libraries
Classifier: Topic :: Software Development :: Libraries :: Python Modules
Classifier: Topic :: Software Development :: Testing
Classifier: Topic :: Software Development :: Testing :: Unit
Requires-Dist: termcolor (>=2.3.0,<3.0.0)
Project-URL: Changelog, https://github.com/fullstack-spiderman/unittestx/releases
Project-URL: Documentation, https://github.com/fullstack-spiderman/unittestx#readme
Project-URL: Repository, https://github.com/fullstack-spiderman/unittestx
